{
  "name": "Laura Bowman",
  "age": 62,
  "address": {
    "street": "Aludim Extension",
    "city": "Nofivrad",
    "state": "KY",
    "zip": "57519"
  },
  "contact": {
    "phone": "(338) 783-5179",
    "servicePhone": "800437345"
  },
  "birthday": "2006-08-26T22:23:38.792Z",
  "ip": "175.232.9.78",
  "foo": "bar",
  "profile": {
    "about": "Ko ru vufhi no sif ve on zuwnu fiboshu jisjokfow ga bo li raodeg. Sopozluc be vobsohnes omi seg tatas ug kew vadis fumu dormodut pubgadle fiz ipu gis enagzov. Rokfe opru iwo lug to pejrolpon wivtaz bu pivdaj kaapi jip giwouwa nel tuku. Rapreb luv vascotkop wovidko ve kodisda mi uco aj fo wejetetun rir. Sa tasactuw befuho riwuvu kitvukef miwuz wo vu jewu liz moloto menzanfav fep. Ci tepiov gudop for fet ho jukewoja eci ka ejgipov hukik hiz cos. Cowa bugwalko ajromit utenovula mulodma panatovom hu re uwgesgi ejane tabocu feg.",
    "bio": "Ulto oj tizjevo fuez wonwan amo otababvo iwka um saokupu ubegugi edtu zeaf. Ofuapig dovinaz rewugves hew tadpi no ijuhokto do eh hujedwa acimul unwedur. Negbun piholsa biwiavu vubuv ure ju dewgen iku obdaz vutpo duwohaped ufalozol laezu. Gus hunvirpef wovewhig kuit sipduro teg ri monogu gimasov gopdefku patoc rumcog pupmeaz jef woselur oze bucod."
  },
  "apiKey": "d4b7ceab468d328eac66977ede0cb278b77c781490092f408d8bc09a8bc48711",
  "currency": {
    "code": "THB",
    "name": "Thailand Baht"
  }
}